odoo/addons/survey_question_type_binary_result_mail/README.rst
odoo/addons/survey_question_type_binary_result_mail/__init__.py
odoo/addons/survey_question_type_binary_result_mail/__manifest__.py
odoo/addons/survey_question_type_binary_result_mail/i18n/survey_question_type_binary_result_mail.pot
odoo/addons/survey_question_type_binary_result_mail/models/__init__.py
odoo/addons/survey_question_type_binary_result_mail/models/survey_user_input.py
odoo/addons/survey_question_type_binary_result_mail/readme/CONTRIBUTORS.rst
odoo/addons/survey_question_type_binary_result_mail/readme/DESCRIPTION.rst
odoo/addons/survey_question_type_binary_result_mail/static/description/icon.png
odoo/addons/survey_question_type_binary_result_mail/static/description/index.html
odoo_addon_survey_question_type_binary_result_mail-15.0.1.0.0.2.dist-info/METADATA
odoo_addon_survey_question_type_binary_result_mail-15.0.1.0.0.2.dist-info/WHEEL
odoo_addon_survey_question_type_binary_result_mail-15.0.1.0.0.2.dist-info/top_level.txt
odoo_addon_survey_question_type_binary_result_mail-15.0.1.0.0.2.dist-info/RECORD
