Metadata-Version: 2.1
Name: odoo-addon-survey_question_type_binary_result_mail
Version: 15.0.1.0.0.2
Summary: Send survey answers to the survey user
Home-page: https://github.com/OCA/survey
Author: Grupo Isonor, Odoo Community Association (OCA)
Author-email: support@odoo-community.org
License: AGPL-3
Classifier: Programming Language :: Python
Classifier: Framework :: Odoo
Classifier: Framework :: Odoo :: 15.0
Classifier: License :: OSI Approved :: GNU Affero General Public License v3
Classifier: Development Status :: 4 - Beta
Requires-Python: >=3.8
Requires-Dist: odoo-addon-survey-question-type-binary<15.1dev,>=15.0dev
Requires-Dist: odoo-addon-survey-result-mail<15.1dev,>=15.0dev
Requires-Dist: odoo<15.1dev,>=15.0a
